pollination/honeybee_energy/__init__.py
pollination/honeybee_energy/baseline.py
pollination/honeybee_energy/result.py
pollination/honeybee_energy/settings.py
pollination/honeybee_energy/simulate.py
pollination/honeybee_energy/translate.py
pollination_honeybee_energy-0.7.16.dist-info/LICENSE
pollination_honeybee_energy-0.7.16.dist-info/METADATA
pollination_honeybee_energy-0.7.16.dist-info/WHEEL
pollination_honeybee_energy-0.7.16.dist-info/top_level.txt
pollination_honeybee_energy-0.7.16.dist-info/RECORD
