Metadata-Version: 2.1
Name: pollination-honeybee-energy
Version: 0.7.16
Summary: Honeybee energy plugin for Pollination.
Home-page: https://github.com/pollination/honeybee-energy
Author: ladybug-tools
Author-email: chris@ladybug.tools
Maintainer: Chris, ladybug-tools
Maintainer-email: chris@ladybug.tools, info@ladybug.tools
License: PolyForm Shield License 1.0.0, https://polyformproject.org/wp-content/uploads/2020/06/PolyForm-Shield-1.0.0.txt
Project-URL: icon, https://raw.githubusercontent.com/ladybug-tools/artwork/master/icons_bugs/grasshopper_tabs/HB-Energy.png
Project-URL: docker, https://hub.docker.com/r/ladybugtools/honeybee-energy
Keywords: honeybee,energy,ladybug-tools
License-File: LICENSE
Requires-Dist: pollination-dsl>=0.17.1
Requires-Dist: honeybee-energy>=1.116.90
